Metadata-Version: 2.1
Name: monilogger
Version: 0.0.1
Summary: A Python logging and monitoring toolbox for C++ applications.
Home-page: https://github.com/cea-hpc/monilog
Author: Dorian Leroy
Author-email: dorian.leroy@cea.fr
License: UNKNOWN
Platform: UNKNOWN
Requires-Python: >=3.6
Provides-Extra: test
